{
    "info": [
        {
            "description": "cerastoderma",
            "creator": "세명소프트",
            "distributor": "세명소프트",
            "region_name": "충남수산자원연구소"
        }
    ],
    "categories": [
        {
            "id": 1,
            "name": "바지락_수정란",
            "supercategory": "바지락"
        },
        {
            "id": 2,
            "name": "바지락_유생",
            "supercategory": "바지락"
        },
        {
            "id": 3,
            "name": "바지락_치패",
            "supercategory": "바지락"
        },
        {
            "id": 4,
            "name": "바지락_유생폐사",
            "supercategory": "바지락"
        }
    ],
    "object_info": {
        "shoot_info": {
            "classification": "치패",
            "equipment_name": "고배율 광학현미경",
            "file_name": "MA_MG_220731",
            "b_date": "2022-07-07",
            "s_date": "2022-07-22",
            "m_date": "2022-07-22",
            "f_date": "2022-07-31",
            "a_time": null,
            "region_name": "충남수산자원연구소",
            "magnification": "100",
            "pixel_constant": 1.7860465116279067
        },
        "manage_info": {
            "water_tank": "A1-04",
            "a_day": "24",
            "tank_size": "10",
            "mean_shell_length": "221"
        },
        "water_info": {
            "replaced_water": "Yes",
            "filter": "Yes",
            "UV": "Yes",
            "EDTA": "No",
            "antibiotic": "No"
        },
        "feed_info": {
            "Iso_cells": "785",
            "Chaeto_cells": "585",
            "Tet_cells": "595",
            "Iso_fed": "20",
            "Chaeto_fed": "20",
            "Tet_fed": "20"
        },
        "observe_info": {
            "color": "Good",
            "vitality": "Yes",
            "sample_liter": "0.0",
            "count": "0,0,0",
            "object_density": "0",
            "object_amount": ""
        }
    },
    "images": [
        {
            "id": 1531,
            "file_name": "MA_MS_100_Sp_220731_1000 (3).jpg",
            "sensor_info": {
                "water_temp": "26.78",
                "salinity": "29.95",
                "DO": "6.95",
                "pH": "7.8"
            },
            "width": 960,
            "height": 608
        }
    ],
    "annotations": [
        {
            "id": 3330,
            "image_id": 1531,
            "category_id": 3,
            "segmentation": [
                [
                    374.5,
                    350.1,
                    375.54,
                    334.77,
                    377.1,
                    326.5,
                    379.16,
                    318.16,
                    382.48,
                    309.1,
                    385.8,
                    302.5,
                    389.1,
                    296.1,
                    393.35,
                    289.17,
                    398.49,
                    283.74,
                    403.5,
                    279.5,
                    411.8,
                    274.8,
                    417.81,
                    271.96,
                    425.96,
                    270.45,
                    432.0,
                    269.85,
                    438.35,
                    269.85,
                    447.4,
                    269.55,
                    451.03,
                    269.24,
                    464.92,
                    270.45,
                    469.45,
                    272.26,
                    472.77,
                    276.79,
                    474.9,
                    281.2,
                    477.6,
                    284.04,
                    479.41,
                    291.29,
                    480.32,
                    298.23,
                    480.32,
                    306.69,
                    479.9,
                    312.9,
                    478.81,
                    319.37,
                    478.2,
                    325.41,
                    476.7,
                    331.45,
                    473.5,
                    337.5,
                    469.75,
                    342.92,
                    467.33,
                    345.64,
                    462.5,
                    350.47,
                    458.58,
                    355.0,
                    454.95,
                    357.72,
                    448.61,
                    361.04,
                    440.76,
                    364.06,
                    434.42,
                    366.48,
                    427.3,
                    368.3,
                    418.72,
                    369.8,
                    411.47,
                    369.8,
                    403.92,
                    368.59,
                    394.86,
                    367.08,
                    388.82,
                    365.27,
                    386.9,
                    355.6,
                    376.8,
                    354.8
                ]
            ],
            "area": 8360.0,
            "bbox": [
                374.5,
                269.24,
                105.82,
                100.56
            ],
            "iscrowd": 0,
            "attributes": {
                "occluded": false
            },
            "class_alive": "True",
            "shell_size": 221.62004755773734
        }
    ]
}